evaris/__init__.py
evaris/_async_helpers.py
evaris/agent_interface.py
evaris/baselines.py
evaris/compliance.py
evaris/contamination.py
evaris/dataset.py
evaris/evaluate.py
evaris/oracle.py
evaris/statistics.py
evaris/tracing.py
evaris/types.py
evaris/validation.py
evaris/metrics/__init__.py
evaris/metrics/answer_match.py
evaris/metrics/exact_match.py
evaris/metrics/fuzz_test.py
evaris/metrics/llm_judge.py
evaris/metrics/semantic_similarity.py
evaris/metrics/state_match.py
evaris/metrics/unit_test.py
evaris/wrappers/__init__.py
evaris/wrappers/base.py
evaris/wrappers/conversation.py
evaris/wrappers/langchain.py
evaris/wrappers/simple.py
evaris-0.0.1.dev1.dist-info/METADATA
evaris-0.0.1.dev1.dist-info/WHEEL
evaris-0.0.1.dev1.dist-info/licenses/LICENSE
evaris-0.0.1.dev1.dist-info/RECORD
