Metadata-Version: 2.4
Name: evaris
Version: 0.0.1.dev1
Summary: AI Agent Evaluation and Observability Framework
Project-URL: Homepage, https://github.com/swaingotnochill/evaris
Project-URL: Documentation, https://docs.evaris.dev
Project-URL: Repository, https://github.com/swaingotnochill/evaris
Project-URL: Issues, https://github.com/swaingotnochill/evaris/issues
Author-email: Roshan Nrusing Swain <swaingotnochill@gmail.com>
License: Apache-2.0
License-File: LICENSE
Keywords: agents,ai,evaluation,llm,observability,testing
Classifier: Development Status :: 3 - Alpha
Classifier: Intended Audience :: Developers
Classifier: License :: OSI Approved :: Apache Software License
Classifier: Programming Language :: Python :: 3
Classifier: Programming Language :: Python :: 3.9
Classifier: Programming Language :: Python :: 3.10
Classifier: Programming Language :: Python :: 3.11
Classifier: Programming Language :: Python :: 3.12
Requires-Python: >=3.9
Requires-Dist: pydantic>=2.0.0
Requires-Dist: typing-extensions>=4.0.0
Provides-Extra: all
Requires-Dist: anthropic>=0.18.0; extra == 'all'
Requires-Dist: dashscope>=1.14.0; extra == 'all'
Requires-Dist: google-generativeai>=0.3.0; extra == 'all'
Requires-Dist: openai>=1.0.0; extra == 'all'
Requires-Dist: opentelemetry-api>=1.20.0; extra == 'all'
Requires-Dist: opentelemetry-exporter-otlp>=1.20.0; extra == 'all'
Requires-Dist: opentelemetry-sdk>=1.20.0; extra == 'all'
Requires-Dist: rich>=13.0.0; extra == 'all'
Requires-Dist: sentence-transformers>=2.2.0; extra == 'all'
Requires-Dist: torch>=2.0.0; extra == 'all'
Provides-Extra: dev
Requires-Dist: anthropic>=0.18.0; extra == 'dev'
Requires-Dist: black>=23.0.0; extra == 'dev'
Requires-Dist: dashscope>=1.14.0; extra == 'dev'
Requires-Dist: google-generativeai>=0.3.0; extra == 'dev'
Requires-Dist: mypy>=1.0.0; extra == 'dev'
Requires-Dist: openai>=1.0.0; extra == 'dev'
Requires-Dist: opentelemetry-api>=1.20.0; extra == 'dev'
Requires-Dist: opentelemetry-exporter-otlp>=1.20.0; extra == 'dev'
Requires-Dist: opentelemetry-sdk>=1.20.0; extra == 'dev'
Requires-Dist: pytest-asyncio>=0.21.0; extra == 'dev'
Requires-Dist: pytest-cov>=4.0.0; extra == 'dev'
Requires-Dist: pytest>=7.0.0; extra == 'dev'
Requires-Dist: python-dotenv>=1.0.0; extra == 'dev'
Requires-Dist: rich>=13.0.0; extra == 'dev'
Requires-Dist: ruff>=0.1.0; extra == 'dev'
Requires-Dist: sentence-transformers>=2.2.0; extra == 'dev'
Requires-Dist: torch>=2.0.0; extra == 'dev'
Provides-Extra: llm
Requires-Dist: anthropic>=0.18.0; extra == 'llm'
Requires-Dist: dashscope>=1.14.0; extra == 'llm'
Requires-Dist: google-generativeai>=0.3.0; extra == 'llm'
Requires-Dist: openai>=1.0.0; extra == 'llm'
Provides-Extra: semantic
Requires-Dist: sentence-transformers>=2.2.0; extra == 'semantic'
Requires-Dist: torch>=2.0.0; extra == 'semantic'
Provides-Extra: tracing
Requires-Dist: opentelemetry-api>=1.20.0; extra == 'tracing'
Requires-Dist: opentelemetry-exporter-otlp>=1.20.0; extra == 'tracing'
Requires-Dist: opentelemetry-sdk>=1.20.0; extra == 'tracing'
Provides-Extra: ui
Requires-Dist: rich>=13.0.0; extra == 'ui'
